{
  "impressions_history_videos_watched": [
    {
      "string_map_data": {
        "Author": {
          "value": "kushal_me08"
        },
        "Time": {
          "timestamp": 1751983703
        }
      }
    },
    {
      "string_map_data": {
        "Author": {
          "value": "netflix_in"
        },
        "Time": {
          "timestamp": 1751988329
        }
      }
    },
    {
      "string_map_data": {
        "Author": {
          "value": "pinkzpublicschool"
        },
        "Time": {
          "timestamp": 1751995751
        }
      }
    },
    {
      "string_map_data": {
        "Author": {
          "value": "justnowarani"
        },
        "Time": {
          "timestamp": 1752025898
        }
      }
    },
    {
      "string_map_data": {
        "Author": {
          "value": "royalvellore"
        },
        "Time": {
          "timestamp": 1752046741
        }
      }
    },
    {
      "string_map_data": {
        "Author": {
          "value": "_syedrb096_"
        },
        "Time": {
          "timestamp": 1752069690
        }
      }
    },
    {
      "string_map_data": {
        "Author": {
          "value": "aranimapillai"
        },
        "Time": {
          "timestamp": 1752069690
        }
      }
    },
    {
      "string_map_data": {
        "Author": {
          "value": "vellore_vit"
        },
        "Time": {
          "timestamp": 1752085126
        }
      }
    },
    {
      "string_map_data": {
        "Author": {
          "value": "hahahariniii._"
        },
        "Time": {
          "timestamp": 1752085224
        }
      }
    },
    {
      "string_map_data": {
        "Author": {
          "value": "sreeleela14"
        },
        "Time": {
          "timestamp": 1752086336
        }
      }
    },
    {
      "string_map_data": {
        "Author": {
          "value": "rsquared_7"
        },
        "Time": {
          "timestamp": 1752110413
        }
      }
    },
    {
      "string_map_data": {
        "Author": {
          "value": "preetha_asp"
        },
        "Time": {
          "timestamp": 1752122852
        }
      }
    },
    {
      "string_map_data": {
        "Author": {
          "value": "_kishanthofficial_"
        },
        "Time": {
          "timestamp": 1752122949
        }
      }
    },
    {
      "string_map_data": {
        "Author": {
          "value": "kushakapila"
        },
        "Time": {
          "timestamp": 1752123244
        }
      }
    },
    {
      "string_map_data": {
        "Author": {
          "value": "netflix_in"
        },
        "Time": {
          "timestamp": 1752123372
        }
      }
    },
    {
      "string_map_data": {
        "Author": {
          "value": "vijay.krishnxx"
        },
        "Time": {
          "timestamp": 1752123372
        }
      }
    },
    {
      "string_map_data": {
        "Author": {
          "value": "tick_your_tour_"
        },
        "Time": {
          "timestamp": 1752124952
        }
      }
    },
    {
      "string_map_data": {
        "Author": {
          "value": "dk_views_dj"
        },
        "Time": {
          "timestamp": 1752125191
        }
      }
    },
    {
      "string_map_data": {
        "Author": {
          "value": "netflix_in"
        },
        "Time": {
          "timestamp": 1752125191
        }
      }
    },
    {
      "string_map_data": {
        "Author": {
          "value": "flarespell.official"
        },
        "Time": {
          "timestamp": 1752125875
        }
      }
    },
    {
      "string_map_data": {
        "Author": {
          "value": "zaradigitalprinters"
        },
        "Time": {
          "timestamp": 1752128618
        }
      }
    },
    {
      "string_map_data": {
        "Author": {
          "value": "tharamana__templates"
        },
        "Time": {
          "timestamp": 1752128729
        }
      }
    },
    {
      "string_map_data": {
        "Author": {
          "value": "weareflashoot"
        },
        "Time": {
          "timestamp": 1752129979
        }
      }
    },
    {
      "string_map_data": {
        "Author": {
          "value": "netflix_in"
        },
        "Time": {
          "timestamp": 1752133947
        }
      }
    },
    {
      "string_map_data": {
        "Author": {
          "value": "shankarmahadevanacademy"
        },
        "Time": {
          "timestamp": 1752143386
        }
      }
    },
    {
      "string_map_data": {
        "Author": {
          "value": "arani.junction"
        },
        "Time": {
          "timestamp": 1752143386
        }
      }
    },
    {
      "string_map_data": {
        "Author": {
          "value": "jini_sundarraj"
        },
        "Time": {
          "timestamp": 1752146384
        }
      }
    },
    {
      "string_map_data": {
        "Author": {
          "value": "thepixelphotography"
        },
        "Time": {
          "timestamp": 1752146531
        }
      }
    },
    {
      "string_map_data": {
        "Author": {
          "value": "weareflashoot"
        },
        "Time": {
          "timestamp": 1752146586
        }
      }
    },
    {
      "string_map_data": {
        "Author": {
          "value": "vellore_third_eye"
        },
        "Time": {
          "timestamp": 1752146586
        }
      }
    },
    {
      "string_map_data": {
        "Author": {
          "value": "mr_xoxo_pilot"
        },
        "Time": {
          "timestamp": 1752146586
        }
      }
    },
    {
      "string_map_data": {
        "Author": {
          "value": "aranimapillai"
        },
        "Time": {
          "timestamp": 1752146586
        }
      }
    },
    {
      "string_map_data": {
        "Author": {
          "value": "netflix_in"
        },
        "Time": {
          "timestamp": 1752146586
        }
      }
    },
    {
      "string_map_data": {
        "Author": {
          "value": "madhampatty_rangaraj"
        },
        "Time": {
          "timestamp": 1752146586
        }
      }
    },
    {
      "string_map_data": {
        "Author": {
          "value": "vit.logy"
        },
        "Time": {
          "timestamp": 1752147129
        }
      }
    },
    {
      "string_map_data": {
        "Author": {
          "value": "justnowarani"
        },
        "Time": {
          "timestamp": 1752148564
        }
      }
    },
    {
      "string_map_data": {
        "Author": {
          "value": "olam.live"
        },
        "Time": {
          "timestamp": 1752148564
        }
      }
    },
    {
      "string_map_data": {
        "Author": {
          "value": "weareflashoot"
        },
        "Time": {
          "timestamp": 1752148564
        }
      }
    },
    {
      "string_map_data": {
        "Author": {
          "value": "netflix_in"
        },
        "Time": {
          "timestamp": 1752148564
        }
      }
    },
    {
      "string_map_data": {
        "Author": {
          "value": "varnam_weddings_events"
        },
        "Time": {
          "timestamp": 1752151098
        }
      }
    },
    {
      "string_map_data": {
        "Author": {
          "value": "ishaanghosh"
        },
        "Time": {
          "timestamp": 1752151098
        }
      }
    },
    {
      "string_map_data": {
        "Author": {
          "value": "netflix_in"
        },
        "Time": {
          "timestamp": 1752151103
        }
      }
    },
    {
      "string_map_data": {
        "Author": {
          "value": "vayadi_rukki"
        },
        "Time": {
          "timestamp": 1752151103
        }
      }
    },
    {
      "string_map_data": {
        "Author": {
          "value": "tharamana__templates"
        },
        "Time": {
          "timestamp": 1752151103
        }
      }
    },
    {
      "string_map_data": {
        "Author": {
          "value": "sonymusicindia"
        },
        "Time": {
          "timestamp": 1752152985
        }
      }
    },
    {
      "string_map_data": {
        "Author": {
          "value": "justnowarani"
        },
        "Time": {
          "timestamp": 1752154396
        }
      }
    },
    {
      "string_map_data": {
        "Author": {
          "value": "rajasekar_c_"
        },
        "Time": {
          "timestamp": 1752156400
        }
      }
    },
    {
      "string_map_data": {
        "Author": {
          "value": "netflix_in"
        },
        "Time": {
          "timestamp": 1752156565
        }
      }
    },
    {
      "string_map_data": {
        "Author": {
          "value": "vayadi_rukki"
        },
        "Time": {
          "timestamp": 1752157536
        }
      }
    },
    {
      "string_map_data": {
        "Author": {
          "value": "arani.junction"
        },
        "Time": {
          "timestamp": 1752195683
        }
      }
    },
    {
      "string_map_data": {
        "Author": {
          "value": "justnowarani"
        },
        "Time": {
          "timestamp": 1752201789
        }
      }
    },
    {
      "string_map_data": {
        "Author": {
          "value": "dineshbsaravanan"
        },
        "Time": {
          "timestamp": 1752201795
        }
      }
    },
    {
      "string_map_data": {
        "Author": {
          "value": "sk_wedding_plannerr"
        },
        "Time": {
          "timestamp": 1752207240
        }
      }
    },
    {
      "string_map_data": {
        "Author": {
          "value": "royalvellore"
        },
        "Time": {
          "timestamp": 1752207240
        }
      }
    },
    {
      "string_map_data": {
        "Author": {
          "value": "annaimira_clg_engg_tech_vlr"
        },
        "Time": {
          "timestamp": 1752207253
        }
      }
    },
    {
      "string_map_data": {
        "Author": {
          "value": "aarogyaclinic_vellore"
        },
        "Time": {
          "timestamp": 1752215443
        }
      }
    },
    {
      "string_map_data": {
        "Author": {
          "value": "netflix_in"
        },
        "Time": {
          "timestamp": 1752219343
        }
      }
    },
    {
      "string_map_data": {
        "Author": {
          "value": "justnowarani"
        },
        "Time": {
          "timestamp": 1752226447
        }
      }
    },
    {
      "string_map_data": {
        "Author": {
          "value": "preity_mukhundhan"
        },
        "Time": {
          "timestamp": 1752241673
        }
      }
    },
    {
      "string_map_data": {
        "Author": {
          "value": "s.manikandan___"
        },
        "Time": {
          "timestamp": 1752241673
        }
      }
    },
    {
      "string_map_data": {
        "Author": {
          "value": "royalvellore"
        },
        "Time": {
          "timestamp": 1752241673
        }
      }
    },
    {
      "string_map_data": {
        "Author": {
          "value": "sreeleela14"
        },
        "Time": {
          "timestamp": 1752241926
        }
      }
    },
    {
      "string_map_data": {
        "Author": {
          "value": "punchmelapunch"
        },
        "Time": {
          "timestamp": 1752241949
        }
      }
    },
    {
      "string_map_data": {
        "Author": {
          "value": "pinkzpublicschool"
        },
        "Time": {
          "timestamp": 1752244152
        }
      }
    },
    {
      "string_map_data": {
        "Author": {
          "value": "netflix_in"
        },
        "Time": {
          "timestamp": 1752249439
        }
      }
    },
    {
      "string_map_data": {
        "Author": {
          "value": "weareflashoot"
        },
        "Time": {
          "timestamp": 1752249439
        }
      }
    },
    {
      "string_map_data": {
        "Author": {
          "value": "pinkzpublicschool"
        },
        "Time": {
          "timestamp": 1752249838
        }
      }
    },
    {
      "string_map_data": {
        "Author": {
          "value": "netflix_in"
        },
        "Time": {
          "timestamp": 1752249866
        }
      }
    },
    {
      "string_map_data": {
        "Author": {
          "value": "wwe_on_netflix"
        },
        "Time": {
          "timestamp": 1752250073
        }
      }
    },
    {
      "string_map_data": {
        "Author": {
          "value": "netflix_in"
        },
        "Time": {
          "timestamp": 1752254582
        }
      }
    },
    {
      "string_map_data": {
        "Author": {
          "value": "mr_gentelman__03"
        },
        "Time": {
          "timestamp": 1752254582
        }
      }
    },
    {
      "string_map_data": {
        "Author": {
          "value": "sk_wedding_plannerr"
        },
        "Time": {
          "timestamp": 1752289552
        }
      }
    },
    {
      "string_map_data": {
        "Author": {
          "value": "vayadi_rukki"
        },
        "Time": {
          "timestamp": 1752289565
        }
      }
    },
    {
      "string_map_data": {
        "Author": {
          "value": "vaseegrah"
        },
        "Time": {
          "timestamp": 1752289603
        }
      }
    },
    {
      "string_map_data": {
        "Author": {
          "value": "vanillaskies.co"
        },
        "Time": {
          "timestamp": 1752289603
        }
      }
    },
    {
      "string_map_data": {
        "Author": {
          "value": "justnowarani"
        },
        "Time": {
          "timestamp": 1752291554
        }
      }
    },
    {
      "string_map_data": {
        "Author": {
          "value": "royalvellore"
        },
        "Time": {
          "timestamp": 1752292241
        }
      }
    },
    {
      "string_map_data": {
        "Author": {
          "value": "shreyasgroup"
        },
        "Time": {
          "timestamp": 1752293073
        }
      }
    },
    {
      "string_map_data": {
        "Author": {
          "value": "gokul_shivu_56"
        },
        "Time": {
          "timestamp": 1752297236
        }
      }
    },
    {
      "string_map_data": {
        "Author": {
          "value": "sk_wedding_plannerr"
        },
        "Time": {
          "timestamp": 1752297392
        }
      }
    },
    {
      "string_map_data": {
        "Author": {
          "value": "sunpictures"
        },
        "Time": {
          "timestamp": 1752297392
        }
      }
    },
    {
      "string_map_data": {
        "Author": {
          "value": "akshaya_hariharan_"
        },
        "Time": {
          "timestamp": 1752297392
        }
      }
    },
    {
      "string_map_data": {
        "Author": {
          "value": "news18tamilnadu"
        },
        "Time": {
          "timestamp": 1752297393
        }
      }
    },
    {
      "string_map_data": {
        "Author": {
          "value": "weareflashoot"
        },
        "Time": {
          "timestamp": 1752297454
        }
      }
    },
    {
      "string_map_data": {
        "Author": {
          "value": "mr_xoxo_pilot"
        },
        "Time": {
          "timestamp": 1752298303
        }
      }
    },
    {
      "string_map_data": {
        "Author": {
          "value": "royalvellore"
        },
        "Time": {
          "timestamp": 1752298355
        }
      }
    },
    {
      "string_map_data": {
        "Author": {
          "value": "justnowarani"
        },
        "Time": {
          "timestamp": 1752310733
        }
      }
    },
    {
      "string_map_data": {
        "Author": {
          "value": "netflix_in"
        },
        "Time": {
          "timestamp": 1752310780
        }
      }
    },
    {
      "string_map_data": {
        "Author": {
          "value": "netflix_in"
        },
        "Time": {
          "timestamp": 1752310904
        }
      }
    },
    {
      "string_map_data": {
        "Author": {
          "value": "netflix_in"
        },
        "Time": {
          "timestamp": 1752311328
        }
      }
    },
    {
      "string_map_data": {
        "Author": {
          "value": "tharamana__templates"
        },
        "Time": {
          "timestamp": 1752311777
        }
      }
    },
    {
      "string_map_data": {
        "Author": {
          "value": "sk_wedding_plannerr"
        },
        "Time": {
          "timestamp": 1752312328
        }
      }
    },
    {
      "string_map_data": {
        "Author": {
          "value": "tick_your_tour_"
        },
        "Time": {
          "timestamp": 1752314015
        }
      }
    },
    {
      "string_map_data": {
        "Author": {
          "value": "aranimapillai"
        },
        "Time": {
          "timestamp": 1752314062
        }
      }
    },
    {
      "string_map_data": {
        "Author": {
          "value": "sk_wedding_plannerr"
        },
        "Time": {
          "timestamp": 1752325042
        }
      }
    },
    {
      "string_map_data": {
        "Author": {
          "value": "weareflashoot"
        },
        "Time": {
          "timestamp": 1752326732
        }
      }
    },
    {
      "string_map_data": {
        "Author": {
          "value": "lazzofamilysalon"
        },
        "Time": {
          "timestamp": 1752332964
        }
      }
    },
    {
      "string_map_data": {
        "Author": {
          "value": "netflix_in"
        },
        "Time": {
          "timestamp": 1752332964
        }
      }
    },
    {
      "string_map_data": {
        "Author": {
          "value": "akhils_77_"
        },
        "Time": {
          "timestamp": 1752333393
        }
      }
    },
    {
      "string_map_data": {
        "Author": {
          "value": "royalvellore"
        },
        "Time": {
          "timestamp": 1752333690
        }
      }
    },
    {
      "string_map_data": {
        "Author": {
          "value": "netflix_in"
        },
        "Time": {
          "timestamp": 1752336934
        }
      }
    },
    {
      "string_map_data": {
        "Author": {
          "value": "tick_your_tour_"
        },
        "Time": {
          "timestamp": 1752336934
        }
      }
    },
    {
      "string_map_data": {
        "Author": {
          "value": "vayadi_rukki"
        },
        "Time": {
          "timestamp": 1752340268
        }
      }
    },
    {
      "string_map_data": {
        "Author": {
          "value": "dineshbsaravanan"
        },
        "Time": {
          "timestamp": 1752381526
        }
      }
    },
    {
      "string_map_data": {
        "Author": {
          "value": "mr_gentelman__03"
        },
        "Time": {
          "timestamp": 1752389465
        }
      }
    },
    {
      "string_map_data": {
        "Author": {
          "value": "roughnoteproductions"
        },
        "Time": {
          "timestamp": 1752391324
        }
      }
    },
    {
      "string_map_data": {
        "Author": {
          "value": "akshaya_hariharan_"
        },
        "Time": {
          "timestamp": 1752391545
        }
      }
    },
    {
      "string_map_data": {
        "Author": {
          "value": "rsquared_7"
        },
        "Time": {
          "timestamp": 1752392472
        }
      }
    },
    {
      "string_map_data": {
        "Author": {
          "value": "weareflashoot"
        },
        "Time": {
          "timestamp": 1752392491
        }
      }
    },
    {
      "string_map_data": {
        "Author": {
          "value": "sanjay_vivasayi_"
        },
        "Time": {
          "timestamp": 1752399627
        }
      }
    },
    {
      "string_map_data": {
        "Author": {
          "value": "netflix_in"
        },
        "Time": {
          "timestamp": 1752399997
        }
      }
    },
    {
      "string_map_data": {
        "Author": {
          "value": "nmacc.indiaweekend"
        },
        "Time": {
          "timestamp": 1752406241
        }
      }
    },
    {
      "string_map_data": {
        "Author": {
          "value": "vayadi_rukki"
        },
        "Time": {
          "timestamp": 1752406241
        }
      }
    },
    {
      "string_map_data": {
        "Author": {
          "value": "netflix_in"
        },
        "Time": {
          "timestamp": 1752406308
        }
      }
    },
    {
      "string_map_data": {
        "Author": {
          "value": "vellore_vit"
        },
        "Time": {
          "timestamp": 1752417194
        }
      }
    },
    {
      "string_map_data": {
        "Author": {
          "value": "netflix_in"
        },
        "Time": {
          "timestamp": 1752418299
        }
      }
    },
    {
      "string_map_data": {
        "Author": {
          "value": "tiruvannamalaikingdom"
        },
        "Time": {
          "timestamp": 1752422380
        }
      }
    },
    {
      "string_map_data": {
        "Author": {
          "value": "mythpat"
        },
        "Time": {
          "timestamp": 1752423388
        }
      }
    },
    {
      "string_map_data": {
        "Author": {
          "value": "velloreblackyaadhum_oore"
        },
        "Time": {
          "timestamp": 1752453028
        }
      }
    },
    {
      "string_map_data": {
        "Author": {
          "value": "weareflashoot"
        },
        "Time": {
          "timestamp": 1752479002
        }
      }
    },
    {
      "string_map_data": {
        "Author": {
          "value": "justnowarani"
        },
        "Time": {
          "timestamp": 1752479046
        }
      }
    },
    {
      "string_map_data": {
        "Author": {
          "value": "mukeshyashvanth"
        },
        "Time": {
          "timestamp": 1752481463
        }
      }
    },
    {
      "string_map_data": {
        "Author": {
          "value": "lazzofamilysalon"
        },
        "Time": {
          "timestamp": 1752485545
        }
      }
    },
    {
      "string_map_data": {
        "Author": {
          "value": "villagetowncityvlog"
        },
        "Time": {
          "timestamp": 1752495396
        }
      }
    },
    {
      "string_map_data": {
        "Author": {
          "value": "zaideihawimitehuang"
        },
        "Time": {
          "timestamp": 1752512614
        }
      }
    },
    {
      "string_map_data": {
        "Author": {
          "value": "royalvellore"
        },
        "Time": {
          "timestamp": 1752513179
        }
      }
    },
    {
      "string_map_data": {
        "Author": {
          "value": "annaimira_clg_engg_tech_vlr"
        },
        "Time": {
          "timestamp": 1752553823
        }
      }
    },
    {
      "string_map_data": {
        "Author": {
          "value": "varnam_weddings_events"
        },
        "Time": {
          "timestamp": 1752557793
        }
      }
    },
    {
      "string_map_data": {
        "Author": {
          "value": "netflix_in"
        },
        "Time": {
          "timestamp": 1752557793
        }
      }
    },
    {
      "string_map_data": {
        "Author": {
          "value": "vayadi_rukki"
        },
        "Time": {
          "timestamp": 1752557793
        }
      }
    },
    {
      "string_map_data": {
        "Author": {
          "value": "weareflashoot"
        },
        "Time": {
          "timestamp": 1752557793
        }
      }
    },
    {
      "string_map_data": {
        "Author": {
          "value": "sanjay_vivasayi_"
        },
        "Time": {
          "timestamp": 1752557793
        }
      }
    },
    {
      "string_map_data": {
        "Author": {
          "value": "royalvellore"
        },
        "Time": {
          "timestamp": 1752557813
        }
      }
    },
    {
      "string_map_data": {
        "Author": {
          "value": "pinkzpublicschool"
        },
        "Time": {
          "timestamp": 1752557981
        }
      }
    },
    {
      "string_map_data": {
        "Author": {
          "value": "_bannnno_"
        },
        "Time": {
          "timestamp": 1752558182
        }
      }
    },
    {
      "string_map_data": {
        "Author": {
          "value": "_888dark_"
        },
        "Time": {
          "timestamp": 1752558182
        }
      }
    },
    {
      "string_map_data": {
        "Author": {
          "value": "aranipasanga"
        },
        "Time": {
          "timestamp": 1752563234
        }
      }
    },
    {
      "string_map_data": {
        "Author": {
          "value": "justnowarani"
        },
        "Time": {
          "timestamp": 1752563666
        }
      }
    },
    {
      "string_map_data": {
        "Author": {
          "value": "arani.junction"
        },
        "Time": {
          "timestamp": 1752563780
        }
      }
    },
    {
      "string_map_data": {
        "Author": {
          "value": "netflix_in"
        },
        "Time": {
          "timestamp": 1752571554
        }
      }
    },
    {
      "string_map_data": {
        "Author": {
          "value": "netflix_in"
        },
        "Time": {
          "timestamp": 1752571618
        }
      }
    },
    {
      "string_map_data": {
        "Author": {
          "value": "srwhilephotography"
        },
        "Time": {
          "timestamp": 1752571618
        }
      }
    },
    {
      "string_map_data": {
        "Author": {
          "value": "royalvellore"
        },
        "Time": {
          "timestamp": 1752571618
        }
      }
    },
    {
      "string_map_data": {
        "Author": {
          "value": "shankar.mahadevan"
        },
        "Time": {
          "timestamp": 1752571618
        }
      }
    },
    {
      "string_map_data": {
        "Author": {
          "value": "netflix_in"
        },
        "Time": {
          "timestamp": 1752578754
        }
      }
    },
    {
      "string_map_data": {
        "Author": {
          "value": "aranipasanga"
        },
        "Time": {
          "timestamp": 1752578794
        }
      }
    },
    {
      "string_map_data": {
        "Author": {
          "value": "zaradigitalprinters"
        },
        "Time": {
          "timestamp": 1752578795
        }
      }
    },
    {
      "string_map_data": {
        "Author": {
          "value": "lazzofamilysalon"
        },
        "Time": {
          "timestamp": 1752578816
        }
      }
    },
    {
      "string_map_data": {
        "Author": {
          "value": "instagram"
        },
        "Time": {
          "timestamp": 1752578816
        }
      }
    },
    {
      "string_map_data": {
        "Author": {
          "value": "netflix_in"
        },
        "Time": {
          "timestamp": 1752578890
        }
      }
    },
    {
      "string_map_data": {
        "Author": {
          "value": "nmacc.india"
        },
        "Time": {
          "timestamp": 1752578890
        }
      }
    },
    {
      "string_map_data": {
        "Author": {
          "value": "aranipasanga"
        },
        "Time": {
          "timestamp": 1752578890
        }
      }
    },
    {
      "string_map_data": {
        "Author": {
          "value": "tick_your_tour_"
        },
        "Time": {
          "timestamp": 1752578891
        }
      }
    },
    {
      "string_map_data": {
        "Author": {
          "value": "jini_sundarraj"
        },
        "Time": {
          "timestamp": 1752578891
        }
      }
    },
    {
      "string_map_data": {
        "Author": {
          "value": "olam.live"
        },
        "Time": {
          "timestamp": 1752578902
        }
      }
    },
    {
      "string_map_data": {
        "Author": {
          "value": "hindustanwave"
        },
        "Time": {
          "timestamp": 1752578903
        }
      }
    },
    {
      "string_map_data": {
        "Author": {
          "value": "vayadi_rukki"
        },
        "Time": {
          "timestamp": 1752578915
        }
      }
    },
    {
      "string_map_data": {
        "Author": {
          "value": "netflix_in"
        },
        "Time": {
          "timestamp": 1752578915
        }
      }
    },
    {
      "string_map_data": {
        "Author": {
          "value": "shankarmahadevanacademy"
        },
        "Time": {
          "timestamp": 1752578918
        }
      }
    },
    {
      "string_map_data": {
        "Author": {
          "value": "s.manikandan___"
        },
        "Time": {
          "timestamp": 1752585104
        }
      }
    },
    {
      "string_map_data": {
        "Author": {
          "value": "themadrasbrandingcompany"
        },
        "Time": {
          "timestamp": 1752585595
        }
      }
    },
    {
      "string_map_data": {
        "Author": {
          "value": "royalvellore"
        },
        "Time": {
          "timestamp": 1752585612
        }
      }
    },
    {
      "string_map_data": {
        "Author": {
          "value": "ambur.diaries"
        },
        "Time": {
          "timestamp": 1751728786
        }
      }
    },
    {
      "string_map_data": {
        "Author": {
          "value": "instorefashions"
        },
        "Time": {
          "timestamp": 1751808110
        }
      }
    },
    {
      "string_map_data": {
        "Author": {
          "value": "newupdate3.0"
        },
        "Time": {
          "timestamp": 1751982622
        }
      }
    },
    {
      "string_map_data": {
        "Author": {
          "value": "tick_your_tour_"
        },
        "Time": {
          "timestamp": 1751982622
        }
      }
    },
    {
      "string_map_data": {
        "Author": {
          "value": "kushal_me08"
        },
        "Time": {
          "timestamp": 1751983826
        }
      }
    },
    {
      "string_map_data": {
        "Author": {
          "value": "netflix_in"
        },
        "Time": {
          "timestamp": 1751989095
        }
      }
    },
    {
      "string_map_data": {
        "Author": {
          "value": "pinkzpublicschool"
        },
        "Time": {
          "timestamp": 1752025886
        }
      }
    },
    {
      "string_map_data": {
        "Author": {
          "value": "justnowarani"
        },
        "Time": {
          "timestamp": 1752031438
        }
      }
    },
    {
      "string_map_data": {
        "Author": {
          "value": "royalvellore"
        },
        "Time": {
          "timestamp": 1752069515
        }
      }
    },
    {
      "string_map_data": {
        "Author": {
          "value": "_syedrb096_"
        },
        "Time": {
          "timestamp": 1752069673
        }
      }
    },
    {
      "string_map_data": {
        "Author": {
          "value": "aranimapillai"
        },
        "Time": {
          "timestamp": 1752069675
        }
      }
    },
    {
      "string_map_data": {
        "Author": {
          "value": "vellore_vit"
        },
        "Time": {
          "timestamp": 1752085139
        }
      }
    },
    {
      "string_map_data": {
        "Author": {
          "value": "itsbinodsarkar"
        },
        "Time": {
          "timestamp": 1752086086
        }
      }
    },
    {
      "string_map_data": {
        "Author": {
          "value": "hahahariniii._"
        },
        "Time": {
          "timestamp": 1752086086
        }
      }
    },
    {
      "string_map_data": {
        "Author": {
          "value": "sreeleela14"
        },
        "Time": {
          "timestamp": 1752086317
        }
      }
    },
    {
      "string_map_data": {
        "Author": {
          "value": "rsquared_7"
        },
        "Time": {
          "timestamp": 1752118154
        }
      }
    },
    {
      "string_map_data": {
        "Author": {
          "value": "preetha_asp"
        },
        "Time": {
          "timestamp": 1752122841
        }
      }
    },
    {
      "string_map_data": {
        "Author": {
          "value": "_kishanthofficial_"
        },
        "Time": {
          "timestamp": 1752123225
        }
      }
    },
    {
      "string_map_data": {
        "Author": {
          "value": "kushakapila"
        },
        "Time": {
          "timestamp": 1752123359
        }
      }
    },
    {
      "string_map_data": {
        "Author": {
          "value": "netflix_in"
        },
        "Time": {
          "timestamp": 1752124941
        }
      }
    },
    {
      "string_map_data": {
        "Author": {
          "value": "vijay.krishnxx"
        },
        "Time": {
          "timestamp": 1752124941
        }
      }
    },
    {
      "string_map_data": {
        "Author": {
          "value": "tick_your_tour_"
        },
        "Time": {
          "timestamp": 1752124988
        }
      }
    },
    {
      "string_map_data": {
        "Author": {
          "value": "dk_views_dj"
        },
        "Time": {
          "timestamp": 1752125175
        }
      }
    },
    {
      "string_map_data": {
        "Author": {
          "value": "netflix_in"
        },
        "Time": {
          "timestamp": 1752125862
        }
      }
    },
    {
      "string_map_data": {
        "Author": {
          "value": "flarespell.official"
        },
        "Time": {
          "timestamp": 1752126558
        }
      }
    },
    {
      "string_map_data": {
        "Author": {
          "value": "zaradigitalprinters"
        },
        "Time": {
          "timestamp": 1752128698
        }
      }
    },
    {
      "string_map_data": {
        "Author": {
          "value": "tharamana__templates"
        },
        "Time": {
          "timestamp": 1752129958
        }
      }
    },
    {
      "string_map_data": {
        "Author": {
          "value": "weareflashoot"
        },
        "Time": {
          "timestamp": 1752133933
        }
      }
    },
    {
      "string_map_data": {
        "Author": {
          "value": "netflix_in"
        },
        "Time": {
          "timestamp": 1752137023
        }
      }
    },
    {
      "string_map_data": {
        "Author": {
          "value": "shankarmahadevanacademy"
        },
        "Time": {
          "timestamp": 1752143376
        }
      }
    },
    {
      "string_map_data": {
        "Author": {
          "value": "arani.junction"
        },
        "Time": {
          "timestamp": 1752146078
        }
      }
    },
    {
      "string_map_data": {
        "Author": {
          "value": "jini_sundarraj"
        },
        "Time": {
          "timestamp": 1752146482
        }
      }
    },
    {
      "string_map_data": {
        "Author": {
          "value": "thepixelphotography"
        },
        "Time": {
          "timestamp": 1752146533
        }
      }
    },
    {
      "string_map_data": {
        "Author": {
          "value": "vellore_third_eye"
        },
        "Time": {
          "timestamp": 1752146565
        }
      }
    },
    {
      "string_map_data": {
        "Author": {
          "value": "aranimapillai"
        },
        "Time": {
          "timestamp": 1752146565
        }
      }
    },
    {
      "string_map_data": {
        "Author": {
          "value": "madhampatty_rangaraj"
        },
        "Time": {
          "timestamp": 1752146565
        }
      }
    },
    {
      "string_map_data": {
        "Author": {
          "value": "mr_xoxo_pilot"
        },
        "Time": {
          "timestamp": 1752147119
        }
      }
    },
    {
      "string_map_data": {
        "Author": {
          "value": "netflix_in"
        },
        "Time": {
          "timestamp": 1752147119
        }
      }
    },
    {
      "string_map_data": {
        "Author": {
          "value": "justnowarani"
        },
        "Time": {
          "timestamp": 1752148548
        }
      }
    },
    {
      "string_map_data": {
        "Author": {
          "value": "vit.logy"
        },
        "Time": {
          "timestamp": 1752148548
        }
      }
    },
    {
      "string_map_data": {
        "Author": {
          "value": "netflix_in"
        },
        "Time": {
          "timestamp": 1752148548
        }
      }
    },
    {
      "string_map_data": {
        "Author": {
          "value": "wwe_on_netflix"
        },
        "Time": {
          "timestamp": 1752148555
        }
      }
    },
    {
      "string_map_data": {
        "Author": {
          "value": "wwe_on_netflix"
        },
        "Time": {
          "timestamp": 1752148565
        }
      }
    },
    {
      "string_map_data": {
        "Author": {
          "value": "olam.live"
        },
        "Time": {
          "timestamp": 1752148565
        }
      }
    },
    {
      "string_map_data": {
        "Author": {
          "value": "weareflashoot"
        },
        "Time": {
          "timestamp": 1752148565
        }
      }
    },
    {
      "string_map_data": {
        "Author": {
          "value": "vayadi_rukki"
        },
        "Time": {
          "timestamp": 1752149134
        }
      }
    },
    {
      "string_map_data": {
        "Author": {
          "value": "varnam_weddings_events"
        },
        "Time": {
          "timestamp": 1752149134
        }
      }
    },
    {
      "string_map_data": {
        "Author": {
          "value": "ishaanghosh"
        },
        "Time": {
          "timestamp": 1752149134
        }
      }
    },
    {
      "string_map_data": {
        "Author": {
          "value": "netflix_in"
        },
        "Time": {
          "timestamp": 1752149780
        }
      }
    },
    {
      "string_map_data": {
        "Author": {
          "value": "tharamana__templates"
        },
        "Time": {
          "timestamp": 1752152972
        }
      }
    },
    {
      "string_map_data": {
        "Author": {
          "value": "sonymusicindia"
        },
        "Time": {
          "timestamp": 1752154386
        }
      }
    },
    {
      "string_map_data": {
        "Author": {
          "value": "justnowarani"
        },
        "Time": {
          "timestamp": 1752154431
        }
      }
    },
    {
      "string_map_data": {
        "Author": {
          "value": "netflix_in"
        },
        "Time": {
          "timestamp": 1752156553
        }
      }
    },
    {
      "string_map_data": {
        "Author": {
          "value": "rajasekar_c_"
        },
        "Time": {
          "timestamp": 1752156553
        }
      }
    },
    {
      "string_map_data": {
        "Author": {
          "value": "arani.junction"
        },
        "Time": {
          "timestamp": 1752156825
        }
      }
    },
    {
      "string_map_data": {
        "Author": {
          "value": "vayadi_rukki"
        },
        "Time": {
          "timestamp": 1752168158
        }
      }
    },
    {
      "string_map_data": {
        "Author": {
          "value": "arani.junction"
        },
        "Time": {
          "timestamp": 1752197465
        }
      }
    },
    {
      "string_map_data": {
        "Author": {
          "value": "justnowarani"
        },
        "Time": {
          "timestamp": 1752201782
        }
      }
    },
    {
      "string_map_data": {
        "Author": {
          "value": "dineshbsaravanan"
        },
        "Time": {
          "timestamp": 1752202148
        }
      }
    },
    {
      "string_map_data": {
        "Author": {
          "value": "royalvellore"
        },
        "Time": {
          "timestamp": 1752207229
        }
      }
    },
    {
      "string_map_data": {
        "Author": {
          "value": "sk_wedding_plannerr"
        },
        "Time": {
          "timestamp": 1752207240
        }
      }
    },
    {
      "string_map_data": {
        "Author": {
          "value": "annaimira_clg_engg_tech_vlr"
        },
        "Time": {
          "timestamp": 1752215433
        }
      }
    },
    {
      "string_map_data": {
        "Author": {
          "value": "aarogyaclinic_vellore"
        },
        "Time": {
          "timestamp": 1752215786
        }
      }
    },
    {
      "string_map_data": {
        "Author": {
          "value": "netflix_in"
        },
        "Time": {
          "timestamp": 1752226434
        }
      }
    },
    {
      "string_map_data": {
        "Author": {
          "value": "justnowarani"
        },
        "Time": {
          "timestamp": 1752241572
        }
      }
    },
    {
      "string_map_data": {
        "Author": {
          "value": "preity_mukhundhan"
        },
        "Time": {
          "timestamp": 1752241653
        }
      }
    },
    {
      "string_map_data": {
        "Author": {
          "value": "s.manikandan___"
        },
        "Time": {
          "timestamp": 1752241653
        }
      }
    },
    {
      "string_map_data": {
        "Author": {
          "value": "royalvellore"
        },
        "Time": {
          "timestamp": 1752241653
        }
      }
    },
    {
      "string_map_data": {
        "Author": {
          "value": "sreeleela14"
        },
        "Time": {
          "timestamp": 1752242205
        }
      }
    },
    {
      "string_map_data": {
        "Author": {
          "value": "punchmelapunch"
        },
        "Time": {
          "timestamp": 1752242205
        }
      }
    },
    {
      "string_map_data": {
        "Author": {
          "value": "pinkzpublicschool"
        },
        "Time": {
          "timestamp": 1752247769
        }
      }
    },
    {
      "string_map_data": {
        "Author": {
          "value": "netflix_in"
        },
        "Time": {
          "timestamp": 1752249430
        }
      }
    },
    {
      "string_map_data": {
        "Author": {
          "value": "weareflashoot"
        },
        "Time": {
          "timestamp": 1752249430
        }
      }
    },
    {
      "string_map_data": {
        "Author": {
          "value": "sonymusicindia"
        },
        "Time": {
          "timestamp": 1752249785
        }
      }
    },
    {
      "string_map_data": {
        "Author": {
          "value": "royalvellore"
        },
        "Time": {
          "timestamp": 1752249796
        }
      }
    },
    {
      "string_map_data": {
        "Author": {
          "value": "pinkzpublicschool"
        },
        "Time": {
          "timestamp": 1752249857
        }
      }
    },
    {
      "string_map_data": {
        "Author": {
          "value": "netflix_in"
        },
        "Time": {
          "timestamp": 1752249952
        }
      }
    },
    {
      "string_map_data": {
        "Author": {
          "value": "wwe_on_netflix"
        },
        "Time": {
          "timestamp": 1752254085
        }
      }
    },
    {
      "string_map_data": {
        "Author": {
          "value": "netflix_in"
        },
        "Time": {
          "timestamp": 1752254572
        }
      }
    },
    {
      "string_map_data": {
        "Author": {
          "value": "mr_gentelman__03"
        },
        "Time": {
          "timestamp": 1752289548
        }
      }
    },
    {
      "string_map_data": {
        "Author": {
          "value": "sk_wedding_plannerr"
        },
        "Time": {
          "timestamp": 1752289564
        }
      }
    },
    {
      "string_map_data": {
        "Author": {
          "value": "vayadi_rukki"
        },
        "Time": {
          "timestamp": 1752289601
        }
      }
    },
    {
      "string_map_data": {
        "Author": {
          "value": "vanillaskies.co"
        },
        "Time": {
          "timestamp": 1752289601
        }
      }
    },
    {
      "string_map_data": {
        "Author": {
          "value": "vaseegrah"
        },
        "Time": {
          "timestamp": 1752291491
        }
      }
    },
    {
      "string_map_data": {
        "Author": {
          "value": "justnowarani"
        },
        "Time": {
          "timestamp": 1752292237
        }
      }
    },
    {
      "string_map_data": {
        "Author": {
          "value": "royalvellore"
        },
        "Time": {
          "timestamp": 1752293071
        }
      }
    },
    {
      "string_map_data": {
        "Author": {
          "value": "shreyasgroup"
        },
        "Time": {
          "timestamp": 1752297097
        }
      }
    },
    {
      "string_map_data": {
        "Author": {
          "value": "gokul_shivu_56"
        },
        "Time": {
          "timestamp": 1752297234
        }
      }
    },
    {
      "string_map_data": {
        "Author": {
          "value": "sk_wedding_plannerr"
        },
        "Time": {
          "timestamp": 1752297369
        }
      }
    },
    {
      "string_map_data": {
        "Author": {
          "value": "news18tamilnadu"
        },
        "Time": {
          "timestamp": 1752297369
        }
      }
    },
    {
      "string_map_data": {
        "Author": {
          "value": "sunpictures"
        },
        "Time": {
          "timestamp": 1752297369
        }
      }
    },
    {
      "string_map_data": {
        "Author": {
          "value": "akshaya_hariharan_"
        },
        "Time": {
          "timestamp": 1752297369
        }
      }
    },
    {
      "string_map_data": {
        "Author": {
          "value": "weareflashoot"
        },
        "Time": {
          "timestamp": 1752297454
        }
      }
    },
    {
      "string_map_data": {
        "Author": {
          "value": "netflix_in"
        },
        "Time": {
          "timestamp": 1752298300
        }
      }
    },
    {
      "string_map_data": {
        "Author": {
          "value": "mr_xoxo_pilot"
        },
        "Time": {
          "timestamp": 1752298348
        }
      }
    },
    {
      "string_map_data": {
        "Author": {
          "value": "royalvellore"
        },
        "Time": {
          "timestamp": 1752303891
        }
      }
    },
    {
      "string_map_data": {
        "Author": {
          "value": "justnowarani"
        },
        "Time": {
          "timestamp": 1752310776
        }
      }
    },
    {
      "string_map_data": {
        "Author": {
          "value": "asap_apps_._com"
        },
        "Time": {
          "timestamp": 1752310787
        }
      }
    },
    {
      "string_map_data": {
        "Author": {
          "value": "netflix_in"
        },
        "Time": {
          "timestamp": 1752310787
        }
      }
    },
    {
      "string_map_data": {
        "Author": {
          "value": "netflix_in"
        },
        "Time": {
          "timestamp": 1752310899
        }
      }
    },
    {
      "string_map_data": {
        "Author": {
          "value": "netflix_in"
        },
        "Time": {
          "timestamp": 1752311352
        }
      }
    },
    {
      "string_map_data": {
        "Author": {
          "value": "tharamana__templates"
        },
        "Time": {
          "timestamp": 1752312196
        }
      }
    },
    {
      "string_map_data": {
        "Author": {
          "value": "_bannnno_"
        },
        "Time": {
          "timestamp": 1752313924
        }
      }
    },
    {
      "string_map_data": {
        "Author": {
          "value": "sk_wedding_plannerr"
        },
        "Time": {
          "timestamp": 1752313924
        }
      }
    },
    {
      "string_map_data": {
        "Author": {
          "value": "tick_your_tour_"
        },
        "Time": {
          "timestamp": 1752315505
        }
      }
    },
    {
      "string_map_data": {
        "Author": {
          "value": "aranimapillai"
        },
        "Time": {
          "timestamp": 1752315505
        }
      }
    },
    {
      "string_map_data": {
        "Author": {
          "value": "sk_wedding_plannerr"
        },
        "Time": {
          "timestamp": 1752325034
        }
      }
    },
    {
      "string_map_data": {
        "Author": {
          "value": "netflix_in"
        },
        "Time": {
          "timestamp": 1752325034
        }
      }
    },
    {
      "string_map_data": {
        "Author": {
          "value": "fayazzz_here"
        },
        "Time": {
          "timestamp": 1752326725
        }
      }
    },
    {
      "string_map_data": {
        "Author": {
          "value": "weareflashoot"
        },
        "Time": {
          "timestamp": 1752332831
        }
      }
    },
    {
      "string_map_data": {
        "Author": {
          "value": "royalvellore"
        },
        "Time": {
          "timestamp": 1752332960
        }
      }
    },
    {
      "string_map_data": {
        "Author": {
          "value": "akhils_77_"
        },
        "Time": {
          "timestamp": 1752333390
        }
      }
    },
    {
      "string_map_data": {
        "Author": {
          "value": "lazzofamilysalon"
        },
        "Time": {
          "timestamp": 1752333390
        }
      }
    },
    {
      "string_map_data": {
        "Author": {
          "value": "netflix_in"
        },
        "Time": {
          "timestamp": 1752333390
        }
      }
    },
    {
      "string_map_data": {
        "Author": {
          "value": "vellore_vit"
        },
        "Time": {
          "timestamp": 1752333390
        }
      }
    },
    {
      "string_map_data": {
        "Author": {
          "value": "royalvellore"
        },
        "Time": {
          "timestamp": 1752336927
        }
      }
    },
    {
      "string_map_data": {
        "Author": {
          "value": "netflix_in"
        },
        "Time": {
          "timestamp": 1752340266
        }
      }
    },
    {
      "string_map_data": {
        "Author": {
          "value": "tick_your_tour_"
        },
        "Time": {
          "timestamp": 1752340266
        }
      }
    },
    {
      "string_map_data": {
        "Author": {
          "value": "vayadi_rukki"
        },
        "Time": {
          "timestamp": 1752369437
        }
      }
    },
    {
      "string_map_data": {
        "Author": {
          "value": "pinkzpublicschool"
        },
        "Time": {
          "timestamp": 1752375401
        }
      }
    },
    {
      "string_map_data": {
        "Author": {
          "value": "dineshbsaravanan"
        },
        "Time": {
          "timestamp": 1752384637
        }
      }
    },
    {
      "string_map_data": {
        "Author": {
          "value": "mr_gentelman__03"
        },
        "Time": {
          "timestamp": 1752391307
        }
      }
    },
    {
      "string_map_data": {
        "Author": {
          "value": "roughnoteproductions"
        },
        "Time": {
          "timestamp": 1752391365
        }
      }
    },
    {
      "string_map_data": {
        "Author": {
          "value": "akshaya_hariharan_"
        },
        "Time": {
          "timestamp": 1752392468
        }
      }
    },
    {
      "string_map_data": {
        "Author": {
          "value": "rsquared_7"
        },
        "Time": {
          "timestamp": 1752392486
        }
      }
    },
    {
      "string_map_data": {
        "Author": {
          "value": "weareflashoot"
        },
        "Time": {
          "timestamp": 1752393851
        }
      }
    },
    {
      "string_map_data": {
        "Author": {
          "value": "sanjay_vivasayi_"
        },
        "Time": {
          "timestamp": 1752399667
        }
      }
    },
    {
      "string_map_data": {
        "Author": {
          "value": "netflix_in"
        },
        "Time": {
          "timestamp": 1752400450
        }
      }
    },
    {
      "string_map_data": {
        "Author": {
          "value": "nmacc.indiaweekend"
        },
        "Time": {
          "timestamp": 1752406240
        }
      }
    },
    {
      "string_map_data": {
        "Author": {
          "value": "vayadi_rukki"
        },
        "Time": {
          "timestamp": 1752406240
        }
      }
    },
    {
      "string_map_data": {
        "Author": {
          "value": "netflix_in"
        },
        "Time": {
          "timestamp": 1752412181
        }
      }
    },
    {
      "string_map_data": {
        "Author": {
          "value": "vellore_vit"
        },
        "Time": {
          "timestamp": 1752418222
        }
      }
    },
    {
      "string_map_data": {
        "Author": {
          "value": "netflix_in"
        },
        "Time": {
          "timestamp": 1752419454
        }
      }
    },
    {
      "string_map_data": {
        "Author": {
          "value": "aranipasanga"
        },
        "Time": {
          "timestamp": 1752419837
        }
      }
    },
    {
      "string_map_data": {
        "Author": {
          "value": "tiruvannamalaikingdom"
        },
        "Time": {
          "timestamp": 1752422377
        }
      }
    },
    {
      "string_map_data": {
        "Author": {
          "value": "mythpat"
        },
        "Time": {
          "timestamp": 1752453025
        }
      }
    },
    {
      "string_map_data": {
        "Author": {
          "value": "velloreblackyaadhum_oore"
        },
        "Time": {
          "timestamp": 1752478998
        }
      }
    },
    {
      "string_map_data": {
        "Author": {
          "value": "weareflashoot"
        },
        "Time": {
          "timestamp": 1752478998
        }
      }
    },
    {
      "string_map_data": {
        "Author": {
          "value": "justnowarani"
        },
        "Time": {
          "timestamp": 1752481385
        }
      }
    },
    {
      "string_map_data": {
        "Author": {
          "value": "mukeshyashvanth"
        },
        "Time": {
          "timestamp": 1752485491
        }
      }
    },
    {
      "string_map_data": {
        "Author": {
          "value": "lazzofamilysalon"
        },
        "Time": {
          "timestamp": 1752491158
        }
      }
    },
    {
      "string_map_data": {
        "Author": {
          "value": "villagetowncityvlog"
        },
        "Time": {
          "timestamp": 1752498888
        }
      }
    },
    {
      "string_map_data": {
        "Author": {
          "value": "zaideihawimitehuang"
        },
        "Time": {
          "timestamp": 1752513169
        }
      }
    },
    {
      "string_map_data": {
        "Author": {
          "value": "royalvellore"
        },
        "Time": {
          "timestamp": 1752539290
        }
      }
    },
    {
      "string_map_data": {
        "Author": {
          "value": "madhampatty_rangaraj"
        },
        "Time": {
          "timestamp": 1752550430
        }
      }
    },
    {
      "string_map_data": {
        "Author": {
          "value": "annaimira_clg_engg_tech_vlr"
        },
        "Time": {
          "timestamp": 1752553819
        }
      }
    },
    {
      "string_map_data": {
        "Author": {
          "value": "varnam_weddings_events"
        },
        "Time": {
          "timestamp": 1752554643
        }
      }
    },
    {
      "string_map_data": {
        "Author": {
          "value": "vayadi_rukki"
        },
        "Time": {
          "timestamp": 1752554643
        }
      }
    },
    {
      "string_map_data": {
        "Author": {
          "value": "netflix_in"
        },
        "Time": {
          "timestamp": 1752557788
        }
      }
    },
    {
      "string_map_data": {
        "Author": {
          "value": "sanjay_vivasayi_"
        },
        "Time": {
          "timestamp": 1752557788
        }
      }
    },
    {
      "string_map_data": {
        "Author": {
          "value": "royalvellore"
        },
        "Time": {
          "timestamp": 1752557973
        }
      }
    },
    {
      "string_map_data": {
        "Author": {
          "value": "weareflashoot"
        },
        "Time": {
          "timestamp": 1752557973
        }
      }
    },
    {
      "string_map_data": {
        "Author": {
          "value": "pinkzpublicschool"
        },
        "Time": {
          "timestamp": 1752557987
        }
      }
    },
    {
      "string_map_data": {
        "Author": {
          "value": "_888dark_"
        },
        "Time": {
          "timestamp": 1752558179
        }
      }
    },
    {
      "string_map_data": {
        "Author": {
          "value": "_bannnno_"
        },
        "Time": {
          "timestamp": 1752563164
        }
      }
    },
    {
      "string_map_data": {
        "Author": {
          "value": "aranipasanga"
        },
        "Time": {
          "timestamp": 1752563664
        }
      }
    },
    {
      "string_map_data": {
        "Author": {
          "value": "justnowarani"
        },
        "Time": {
          "timestamp": 1752563778
        }
      }
    },
    {
      "string_map_data": {
        "Author": {
          "value": "arani.junction"
        },
        "Time": {
          "timestamp": 1752564184
        }
      }
    },
    {
      "string_map_data": {
        "Author": {
          "value": "wwe_on_netflix"
        },
        "Time": {
          "timestamp": 1752569506
        }
      }
    },
    {
      "string_map_data": {
        "Author": {
          "value": "netflix_in"
        },
        "Time": {
          "timestamp": 1752571588
        }
      }
    },
    {
      "string_map_data": {
        "Author": {
          "value": "netflix_in"
        },
        "Time": {
          "timestamp": 1752571619
        }
      }
    },
    {
      "string_map_data": {
        "Author": {
          "value": "srwhilephotography"
        },
        "Time": {
          "timestamp": 1752571636
        }
      }
    },
    {
      "string_map_data": {
        "Author": {
          "value": "royalvellore"
        },
        "Time": {
          "timestamp": 1752571636
        }
      }
    },
    {
      "string_map_data": {
        "Author": {
          "value": "shankar.mahadevan"
        },
        "Time": {
          "timestamp": 1752571636
        }
      }
    },
    {
      "string_map_data": {
        "Author": {
          "value": "aranipasanga"
        },
        "Time": {
          "timestamp": 1752578789
        }
      }
    },
    {
      "string_map_data": {
        "Author": {
          "value": "zaradigitalprinters"
        },
        "Time": {
          "timestamp": 1752578811
        }
      }
    },
    {
      "string_map_data": {
        "Author": {
          "value": "netflix_in"
        },
        "Time": {
          "timestamp": 1752578819
        }
      }
    },
    {
      "string_map_data": {
        "Author": {
          "value": "lazzofamilysalon"
        },
        "Time": {
          "timestamp": 1752578819
        }
      }
    },
    {
      "string_map_data": {
        "Author": {
          "value": "aranipasanga"
        },
        "Time": {
          "timestamp": 1752578819
        }
      }
    },
    {
      "string_map_data": {
        "Author": {
          "value": "instagram"
        },
        "Time": {
          "timestamp": 1752578819
        }
      }
    },
    {
      "string_map_data": {
        "Author": {
          "value": "nmacc.india"
        },
        "Time": {
          "timestamp": 1752578888
        }
      }
    },
    {
      "string_map_data": {
        "Author": {
          "value": "tick_your_tour_"
        },
        "Time": {
          "timestamp": 1752578888
        }
      }
    },
    {
      "string_map_data": {
        "Author": {
          "value": "wwe_on_netflix"
        },
        "Time": {
          "timestamp": 1752578888
        }
      }
    },
    {
      "string_map_data": {
        "Author": {
          "value": "jini_sundarraj"
        },
        "Time": {
          "timestamp": 1752578896
        }
      }
    },
    {
      "string_map_data": {
        "Author": {
          "value": "hindustanwave"
        },
        "Time": {
          "timestamp": 1752585096
        }
      }
    },
    {
      "string_map_data": {
        "Author": {
          "value": "olam.live"
        },
        "Time": {
          "timestamp": 1752585096
        }
      }
    },
    {
      "string_map_data": {
        "Author": {
          "value": "shankarmahadevanacademy"
        },
        "Time": {
          "timestamp": 1752585096
        }
      }
    },
    {
      "string_map_data": {
        "Author": {
          "value": "vayadi_rukki"
        },
        "Time": {
          "timestamp": 1752585096
        }
      }
    },
    {
      "string_map_data": {
        "Author": {
          "value": "netflix_in"
        },
        "Time": {
          "timestamp": 1752585096
        }
      }
    },
    {
      "string_map_data": {
        "Author": {
          "value": "s.manikandan___"
        },
        "Time": {
          "timestamp": 1752585231
        }
      }
    },
    {
      "string_map_data": {
        "Author": {
          "value": "ajithkumarracing"
        },
        "Time": {
          "timestamp": 1752585231
        }
      }
    },
    {
      "string_map_data": {
        "Author": {
          "value": "themadrasbrandingcompany"
        },
        "Time": {
          "timestamp": 1752585592
        }
      }
    },
    {
      "string_map_data": {
        "Author": {
          "value": "netflix_in"
        },
        "Time": {
          "timestamp": 1752585622
        }
      }
    },
    {
      "string_map_data": {
        "Author": {
          "value": "netflix_in"
        },
        "Time": {
          "timestamp": 1752585622
        }
      }
    },
    {
      "string_map_data": {
        "Author": {
          "value": "royalvellore"
        },
        "Time": {
          "timestamp": 1752585622
        }
      }
    }
  ]
}